roman_datamodels/__init__.py
roman_datamodels/_version.py
roman_datamodels/conftest.py
roman_datamodels/dqflags.py
roman_datamodels/stnode.py
roman_datamodels/table_definitions.py
roman_datamodels/testing.py
roman_datamodels/_stnode/__init__.py
roman_datamodels/_stnode/_converters.py
roman_datamodels/_stnode/_factories.py
roman_datamodels/_stnode/_integration.py
roman_datamodels/_stnode/_mixins.py
roman_datamodels/_stnode/_node.py
roman_datamodels/_stnode/_registry.py
roman_datamodels/_stnode/_schema.py
roman_datamodels/_stnode/_stnode.py
roman_datamodels/_stnode/_stnode.pyi
roman_datamodels/_stnode/_tagged.py
roman_datamodels/datamodels/__init__.py
roman_datamodels/datamodels/_core.py
roman_datamodels/datamodels/_datamodels.py
roman_datamodels/datamodels/_utils.py
roman_datamodels-0.29.1.dist-info/licenses/LICENSE
roman_datamodels-0.29.1.dist-info/METADATA
roman_datamodels-0.29.1.dist-info/WHEEL
roman_datamodels-0.29.1.dist-info/entry_points.txt
roman_datamodels-0.29.1.dist-info/top_level.txt
roman_datamodels-0.29.1.dist-info/RECORD
