Metadata-Version: 2.4
Name: roman_datamodels
Version: 0.29.1
Summary: data models supporting calibration of the Nancy Grace Roman Space Telescope
Author: STScI
Project-URL: issues, https://github.com/spacetelescope/roman_datamodels/issues
Project-URL: repository, https://github.com/spacetelescope/roman_datamodels
Classifier: Intended Audience :: Science/Research
Classifier: Topic :: Scientific/Engineering :: Astronomy
Classifier: Programming Language :: Python :: 3
Requires-Python: >=3.11
License-File: LICENSE
Requires-Dist: asdf>=4.1.0
Requires-Dist: lz4>=4.3.0
Requires-Dist: asdf-astropy>=0.8.0
Requires-Dist: gwcs>=0.19.0
Requires-Dist: numpy>=1.25
Requires-Dist: astropy>=6.0.0
Requires-Dist: rad>=0.29.1
Requires-Dist: asdf-standard>=1.1.0
Requires-Dist: pyarrow>=10.0.1
Requires-Dist: semantic_version>=2.8
Provides-Extra: test
Requires-Dist: pytest>=9.0.0; extra == "test"
Requires-Dist: pytest-doctestplus>=1.2.1; extra == "test"
Requires-Dist: pandas>=2.2.3; extra == "test"
Provides-Extra: docs
Requires-Dist: sphinx; extra == "docs"
Requires-Dist: sphinx-automodapi; extra == "docs"
Requires-Dist: sphinx-rtd-theme; extra == "docs"
Requires-Dist: sphinx-astropy; extra == "docs"
Dynamic: license-file
